keg_storage/__init__.py
keg_storage/cli.py
keg_storage/plugin.py
keg_storage/py.typed
keg_storage/utils.py
keg_storage/version.py
keg_storage/backends/__init__.py
keg_storage/backends/azure.py
keg_storage/backends/base.py
keg_storage/backends/filesystem.py
keg_storage/backends/s3.py
keg_storage/backends/sftp.py
keg_storage/tests/__init__.py
keg_storage/tests/conftest.py
keg_storage/tests/test_backend_azure.py
keg_storage/tests/test_backend_filesystem.py
keg_storage/tests/test_backend_s3.py
keg_storage/tests/test_backend_sftp.py
keg_storage/tests/test_backends.py
keg_storage/tests/test_cli.py
keg_storage/tests/test_lib.py
keg_storage/tests/test_utils.py
keg_storage/tests/test_views.py
keg_storage_ta/__init__.py
keg_storage_ta/app.py
keg_storage_ta/config.py
keg_storage_ta/extensions.py
keg_storage_ta/views.py
KegStorage-0.5.12.dist-info/LICENSE
KegStorage-0.5.12.dist-info/METADATA
KegStorage-0.5.12.dist-info/WHEEL
KegStorage-0.5.12.dist-info/top_level.txt
KegStorage-0.5.12.dist-info/RECORD
