Metadata-Version: 2.1
Name: KegStorage
Version: 0.5.12
Summary: A simple storage interface with multiple backends for use in a Keg app.
Home-page: https://github.com/level12/keg-storage
Author: Level 12 Developers
Author-email: devteam@level12.io
License: BSD
Platform: UNKNOWN
Classifier: Intended Audience :: Developers
Classifier: License :: OSI Approved :: BSD License
Classifier: Operating System :: OS Independent
Classifier: Programming Language :: Python :: 3
Classifier: Programming Language :: Python :: 3.6
Classifier: Programming Language :: Python :: 3.7
License-File: LICENSE
Requires-Dist: arrow
Requires-Dist: authlib
Requires-Dist: humanize
Requires-Dist: BlazeUtils
Provides-Extra: aws
Requires-Dist: boto3 ; extra == 'aws'
Provides-Extra: azure
Requires-Dist: azure-storage-blob (>=12.6.0) ; extra == 'azure'
Provides-Extra: keg
Requires-Dist: kegelements ; extra == 'keg'
Provides-Extra: sftp
Requires-Dist: paramiko ; extra == 'sftp'
Provides-Extra: test
Requires-Dist: azure-storage-blob (>=12.6.0) ; extra == 'test'
Requires-Dist: boto3 ; extra == 'test'
Requires-Dist: flake8 ; extra == 'test'
Requires-Dist: flask-webtest ; extra == 'test'
Requires-Dist: freezegun ; extra == 'test'
Requires-Dist: paramiko ; extra == 'test'
Requires-Dist: pytest ; extra == 'test'
Requires-Dist: pytest-coverage ; extra == 'test'
Requires-Dist: tox ; extra == 'test'
Requires-Dist: wrapt ; extra == 'test'
